wavetable/__init__.py
wavetable/builder.py
wavetable/config.py
wavetable/item.py
wavetable/logger.py
wavetable/visualizer.py
wavetable-0.1.5.dist-info/licenses/LICENSE
wavetable-0.1.5.dist-info/METADATA
wavetable-0.1.5.dist-info/WHEEL
wavetable-0.1.5.dist-info/top_level.txt
wavetable-0.1.5.dist-info/RECORD
